safetypy/__init__.py
safetypy/requirements.txt
safetypy/safetypy.py
safetyculture_sdk_python_beta-2.2.3.dist-info/LICENSE
safetyculture_sdk_python_beta-2.2.3.dist-info/WHEEL
safetyculture_sdk_python_beta-2.2.3.dist-info/METADATA
safetyculture_sdk_python_beta-2.2.3.dist-info/RECORD
