Metadata-Version: 2.1
Name: safetyculture-sdk-python-beta
Version: 2.2.3
Summary: Beta version of the SafetyCulture Python SDK
Author: Edd
Author-email: edward.abrahamsen-mills@safetyculture.io
Requires-Python: >=3.5,<4.0
Classifier: Programming Language :: Python :: 3
Classifier: Programming Language :: Python :: 3.5
Classifier: Programming Language :: Python :: 3.6
Classifier: Programming Language :: Python :: 3.7
Classifier: Programming Language :: Python :: 3.8
Classifier: Programming Language :: Python :: 3.9
Requires-Dist: future (>=0.18.2)
Requires-Dist: pyyaml (>=5.3)
Requires-Dist: questionary (>=1.5.2,<2.0.0)
Requires-Dist: requests (>=2.22.0)
Requires-Dist: tqdm (>=4.48.2,<5.0.0)
